higlass_widget/__init__.py
higlass_widget/widget.js
higlass_widget/widget.py
higlass_widget-0.1.2.dist-info/METADATA
higlass_widget-0.1.2.dist-info/WHEEL
higlass_widget-0.1.2.dist-info/licenses/LICENSE
higlass_widget-0.1.2.dist-info/RECORD
