Metadata-Version: 2.1
Name: higlass-widget
Version: 0.1.2
Summary: A Jupyter Widget for HiGlass
Project-URL: homepage, https://github.com/higlass/higlass-widget
Author-email: Trevor Manz <trevor.j.manz@gmail.com>
License: MIT
License-File: LICENSE
Requires-Python: >=3.8
Requires-Dist: anywidget>=0.6
Provides-Extra: dev
Requires-Dist: black[jupyter]; extra == 'dev'
Requires-Dist: jupyterlab; extra == 'dev'
Requires-Dist: ruff; extra == 'dev'
Requires-Dist: watchfiles; extra == 'dev'
